{"timestamp":"2026-02-15T14:15:03Z","total_attempts":130,"outcomes":{"success":2,"failure":53,"env_failure":23,"skip":52},"success_rate":1.5,"recent":[{"weakness":"function_complexity","outcome":"rollback","ts":"2026-02-15T13:36:48+00:00"},{"weakness":"function_complexity","outcome":"rollback","ts":"2026-02-15T11:47:24+00:00"},{"weakness":"large_scripts","outcome":"rollback","ts":"2026-02-15T11:29:40+00:00"},{"weakness":"large_scripts","outcome":"rollback","ts":"2026-02-15T11:27:35+00:00"},{"weakness":"large_scripts","outcome":"skip","ts":"2026-02-15T11:27:35+00:00"},{"weakness":"large_scripts","outcome":"rollback","ts":"2026-02-15T11:25:31+00:00"},{"weakness":"function_complexity","outcome":"rollback","ts":"2026-02-15T11:20:46+00:00"},{"weakness":"function_complexity","outcome":"env_failure","ts":"2026-02-14T01:43:25+00:00"}],"top_weaknesses":[{"id":"none","attempts":44,"successes":0},{"id":"idle_gaps","attempts":23,"successes":0},{"id":"capability_status_change","attempts":19,"successes":1},{"id":"function_complexity","attempts":14,"successes":0},{"id":"large_scripts","attempts":7,"successes":0},{"id":"low_creativity","attempts":6,"successes":1},{"id":"log_inconsistency","attempts":4,"successes":0},{"id":"all_blacklisted","attempts":3,"successes":0}]}
